{
  "success": true,
  "data": [
    {
      "id": "a5",
      "title": "史上最全Android build.gradle配置详解",
      "desc": "一、Project的build.gradle文件： 对应的build.gradle代码如下： buildscript{}闭包里是gradle脚本...",
      "cover": "https://upload-images.jianshu.io/upload_images/7320376-12dd54466a937f05.png?imageMogr2/auto-orient/strip|imageView2/1/w/300/h/240"
    },
    {
      "id": "a6",
      "title": "彩铅基础10-小水珠绘画过程",
      "desc": "昨天的说太应付了，今天我可是很认真了，趁妹妹睡觉这一个钟认认真真了哈哈哈，其实还是很仓促，笔触十分粗糙，实在太懒得削铅笔了，浪费时间，画完手有点...",
      "cover": "https://upload-images.jianshu.io/upload_images/12756585-3fec9814ef3a3877.jpg?imageMogr2/auto-orient/strip|imageView2/1/w/300/h/240"
    }
  ]
}